[{"model": "sherlock.profile", "pk": 1, "fields": {"user": 1, "picture": "", "first_name": "", "middle_name": "", "last_name": "", "gender": "", "joined": "2016-11-29T20:42:51.338Z"}}, {"model": "sherlock.profile", "pk": 2, "fields": {"user": 2, "picture": "profile_img/8.jpg", "first_name": "Arthur", "middle_name": "", "last_name": "Wade", "gender": "male", "joined": "2016-11-29T20:45:41.170Z"}}, {"model": "sherlock.profile", "pk": 3, "fields": {"user": 3, "picture": "profile_img/9.jpg", "first_name": "patrick", "middle_name": "", "last_name": "campbell", "gender": "male", "joined": "2016-11-29T20:45:41.328Z"}}, {"model": "sherlock.profile", "pk": 4, "fields": {"user": 4, "picture": "profile_img/14.jpg", "first_name": "nathan", "middle_name": "", "last_name": "reyes", "gender": "male", "joined": "2016-11-29T20:45:41.413Z"}}, {"model": "sherlock.profile", "pk": 5, "fields": {"user": 5, "picture": "profile_img/f1.jpg", "first_name": "diane", "middle_name": "", "last_name": "gibson", "gender": "female", "joined": "2016-11-29T20:45:41.484Z"}}, {"model": "sherlock.profile", "pk": 6, "fields": {"user": 6, "picture": "profile_img/f3.jpg", "first_name": "Dolores", "middle_name": "", "last_name": "Barnes", "gender": "female", "joined": "2016-11-29T20:45:41.559Z"}}, {"model": "sherlock.profile", "pk": 7, "fields": {"user": 7, "picture": "profile_img/24.jpg", "first_name": "jacob", "middle_name": "", "last_name": "gomez", "gender": "male", "joined": "2016-11-29T20:45:41.634Z"}}, {"model": "sherlock.profile", "pk": 8, "fields": {"user": 8, "picture": "profile_img/26.jpg", "first_name": "herman", "middle_name": "", "last_name": "McCoy", "gender": "male", "joined": "2016-11-29T20:45:41.706Z"}}, {"model": "sherlock.profile", "pk": 9, "fields": {"user": 9, "picture": "profile_img/f40.jpg", "first_name": "gina", "middle_name": "", "last_name": "walker", "gender": "female", "joined": "2016-11-29T20:45:41.762Z"}}, {"model": "sherlock.profile", "pk": 10, "fields": {"user": 10, "picture": "profile_img/41.jpg", "first_name": "kevin", "middle_name": "", "last_name": "mitchelle", "gender": "male", "joined": "2016-11-29T20:45:41.820Z"}}, {"model": "sherlock.profile", "pk": 11, "fields": {"user": 11, "picture": "profile_img/42.jpg", "first_name": "jerome", "middle_name": "", "last_name": "matthews", "gender": "male", "joined": "2016-11-29T20:45:41.885Z"}}, {"model": "sherlock.profile", "pk": 12, "fields": {"user": 12, "picture": "profile_img/f53.jpg", "first_name": "valerie", "middle_name": "", "last_name": "hunt", "gender": "female", "joined": "2016-11-29T20:46:14.583Z"}}, {"model": "sherlock.profile", "pk": 13, "fields": {"user": 13, "picture": "profile_img/f69.jpg", "first_name": "leta", "middle_name": "", "last_name": "bates", "gender": "female", "joined": "2016-11-29T20:46:14.647Z"}}, {"model": "sherlock.profile", "pk": 14, "fields": {"user": 14, "picture": "profile_img/57.jpg", "first_name": "hector", "middle_name": "", "last_name": "holmes", "gender": "male", "joined": "2016-11-29T20:46:14.710Z"}}, {"model": "sherlock.profile", "pk": 15, "fields": {"user": 15, "picture": "profile_img/61.jpg", "first_name": "stephen", "middle_name": "", "last_name": "walker", "gender": "male", "joined": "2016-11-29T20:46:14.774Z"}}, {"model": "sherlock.profile", "pk": 16, "fields": {"user": 16, "picture": "profile_img/80.jpg", "first_name": "marshall", "middle_name": "", "last_name": "simmmons", "gender": "male", "joined": "2016-11-29T20:46:14.843Z"}}, {"model": "sherlock.profile", "pk": 17, "fields": {"user": 17, "picture": "profile_img/f74.jpg", "first_name": "ava", "middle_name": "", "last_name": "moore", "gender": "female", "joined": "2016-11-29T20:46:14.907Z"}}, {"model": "sherlock.profile", "pk": 18, "fields": {"user": 18, "picture": "profile_img/82.jpg", "first_name": "gregory", "middle_name": "", "last_name": "spencer", "gender": "male", "joined": "2016-11-29T20:46:14.992Z"}}, {"model": "sherlock.profile", "pk": 19, "fields": {"user": 19, "picture": "profile_img/f80.jpg", "first_name": "jennifer", "middle_name": "", "last_name": "ford", "gender": "female", "joined": "2016-11-29T20:46:15.055Z"}}, {"model": "sherlock.profile", "pk": 20, "fields": {"user": 20, "picture": "profile_img/57_dISCRYo.jpg", "first_name": "rafael", "middle_name": "", "last_name": "watts", "gender": "male", "joined": "2016-11-29T20:46:15.122Z"}}, {"model": "sherlock.profile", "pk": 21, "fields": {"user": 21, "picture": "profile_img/f90.jpg", "first_name": "scarlett", "middle_name": "", "last_name": "weaver", "gender": "female", "joined": "2016-11-29T20:46:15.194Z"}}, {"model": "sherlock.about", "pk": 1, "fields": {"user": 1, "biography": "", "birthdate": "1993-06-22", "city_of_birth": "", "state_of_birth": "", "country_of_birth": "", "sex_at_birth": "Male", "eye_color": "Other", "mother_first_name": "", "mother_maiden_name": "", "mother_last_name": "", "father_first_name": "", "father_last_name": "", "birth_hospital": "General Hospital", "searching_for": "Cousin"}}, {"model": "sherlock.about", "pk": 2, "fields": {"user": 2, "biography": "", "birthdate": "1985-06-20", "city_of_birth": "Providence", "state_of_birth": "Rhode Island (RI)", "country_of_birth": "USA", "sex_at_birth": "Male", "eye_color": "Blue", "mother_first_name": "Maria", "mother_maiden_name": "", "mother_last_name": "Wade", "father_first_name": "William", "father_last_name": "Wade", "birth_hospital": "St. Saint Hospital", "searching_for": "Sibling"}}, {"model": "sherlock.about", "pk": 3, "fields": {"user": 3, "biography": "", "birthdate": "1991-11-08", "city_of_birth": "Boston", "state_of_birth": "Massachusetts (MA)", "country_of_birth": "USA", "sex_at_birth": "Male", "eye_color": "Blue", "mother_first_name": "Lea", "mother_maiden_name": "", "mother_last_name": "Campbell", "father_first_name": "", "father_last_name": "Campbell", "birth_hospital": "Duke Hospital", "searching_for": "Parent"}}, {"model": "sherlock.about", "pk": 4, "fields": {"user": 4, "biography": "", "birthdate": "1975-11-03", "city_of_birth": "Jefferson City", "state_of_birth": "Missouri (MO)", "country_of_birth": "USA", "sex_at_birth": "Male", "eye_color": "Blue", "mother_first_name": "", "mother_maiden_name": "", "mother_last_name": "", "father_first_name": "", "father_last_name": "", "birth_hospital": "John Doe Memorial Hospital", "searching_for": "Parent"}}, {"model": "sherlock.about", "pk": 5, "fields": {"user": 5, "biography": "", "birthdate": "1972-04-26", "city_of_birth": "Salt Lake City", "state_of_birth": "Utah (UT)", "country_of_birth": "", "sex_at_birth": "Female", "eye_color": "Gray", "mother_first_name": "", "mother_maiden_name": "", "mother_last_name": "", "father_first_name": "", "father_last_name": "", "birth_hospital": "Sacred Heart Hospital", "searching_for": "Parent"}}, {"model": "sherlock.about", "pk": 6, "fields": {"user": 6, "biography": "", "birthdate": "1982-01-09", "city_of_birth": "Salt Lake City", "state_of_birth": "Utah (UT)", "country_of_birth": "", "sex_at_birth": "Female", "eye_color": "Gray", "mother_first_name": "", "mother_maiden_name": "", "mother_last_name": "", "father_first_name": "", "father_last_name": "", "birth_hospital": "Northwestern Memorial Hospital", "searching_for": "Parent"}}, {"model": "sherlock.about", "pk": 7, "fields": {"user": 7, "biography": "", "birthdate": "1981-06-10", "city_of_birth": "New Orleans", "state_of_birth": "Louisiana (LA)", "country_of_birth": "", "sex_at_birth": "Male", "eye_color": "Blue", "mother_first_name": "", "mother_maiden_name": "", "mother_last_name": "", "father_first_name": "", "father_last_name": "", "birth_hospital": "Northwestern Memorial Hospital", "searching_for": "Parent"}}, {"model": "sherlock.about", "pk": 8, "fields": {"user": 8, "biography": "", "birthdate": "1981-04-06", "city_of_birth": "Providence", "state_of_birth": "Rhode Island (RI)", "country_of_birth": "", "sex_at_birth": "Male", "eye_color": "Gray", "mother_first_name": "", "mother_maiden_name": "", "mother_last_name": "", "father_first_name": "", "father_last_name": "", "birth_hospital": "Duke Hospital", "searching_for": "Child"}}, {"model": "sherlock.about", "pk": 9, "fields": {"user": 9, "biography": "", "birthdate": "1997-05-25", "city_of_birth": "Asheville", "state_of_birth": "North Carolina (NC)", "country_of_birth": "", "sex_at_birth": "Female", "eye_color": "Gray", "mother_first_name": "", "mother_maiden_name": "", "mother_last_name": "", "father_first_name": "", "father_last_name": "", "birth_hospital": "Duke Hospital", "searching_for": "Parent"}}, {"model": "sherlock.about", "pk": 10, "fields": {"user": 10, "biography": "", "birthdate": "1991-11-01", "city_of_birth": "Elgin", "state_of_birth": "South Carolina (SC)", "country_of_birth": "", "sex_at_birth": "Male", "eye_color": "Blue", "mother_first_name": "", "mother_maiden_name": "", "mother_last_name": "", "father_first_name": "", "father_last_name": "", "birth_hospital": "St. Saint Hospital", "searching_for": "Parent"}}, {"model": "sherlock.about", "pk": 11, "fields": {"user": 11, "biography": "", "birthdate": "1997-09-20", "city_of_birth": "Toledo", "state_of_birth": "Ohio (OH)", "country_of_birth": "", "sex_at_birth": "Male", "eye_color": "Blue", "mother_first_name": "", "mother_maiden_name": "", "mother_last_name": "", "father_first_name": "", "father_last_name": "", "birth_hospital": "Northwestern Memorial Hospital", "searching_for": "Parent"}}, {"model": "sherlock.about", "pk": 12, "fields": {"user": 12, "biography": "", "birthdate": "1976-05-21", "city_of_birth": "Asheville", "state_of_birth": "North Carolina (NC)", "country_of_birth": "", "sex_at_birth": "Female", "eye_color": "Brown", "mother_first_name": "", "mother_maiden_name": "", "mother_last_name": "", "father_first_name": "", "father_last_name": "", "birth_hospital": "Mary Black Memorial Hospital", "searching_for": "Child"}}, {"model": "sherlock.about", "pk": 13, "fields": {"user": 13, "biography": "", "birthdate": "1972-05-03", "city_of_birth": "Phoenix", "state_of_birth": "Arizona (AZ)", "country_of_birth": "", "sex_at_birth": "Female", "eye_color": "Brown", "mother_first_name": "", "mother_maiden_name": "", "mother_last_name": "", "father_first_name": "", "father_last_name": "", "birth_hospital": "Johns Hopkins Hospital", "searching_for": "Child"}}, {"model": "sherlock.about", "pk": 14, "fields": {"user": 14, "biography": "", "birthdate": "1990-06-19", "city_of_birth": "Cleveland", "state_of_birth": "Ohio (OH)", "country_of_birth": "", "sex_at_birth": "Male", "eye_color": "Blue", "mother_first_name": "", "mother_maiden_name": "", "mother_last_name": "", "father_first_name": "", "father_last_name": "", "birth_hospital": "Mayo Clinic", "searching_for": "Parent"}}, {"model": "sherlock.about", "pk": 15, "fields": {"user": 15, "biography": "", "birthdate": "1977-10-06", "city_of_birth": "Baltimore", "state_of_birth": "Maryland (MD)", "country_of_birth": "", "sex_at_birth": "Male", "eye_color": "Green", "mother_first_name": "", "mother_maiden_name": "", "mother_last_name": "", "father_first_name": "", "father_last_name": "", "birth_hospital": "Johns Hopkins Hospital", "searching_for": "Child"}}, {"model": "sherlock.about", "pk": 16, "fields": {"user": 16, "biography": "", "birthdate": "1981-08-03", "city_of_birth": "Richmond", "state_of_birth": "Virginia (VA)", "country_of_birth": "", "sex_at_birth": "Male", "eye_color": "Brown", "mother_first_name": "", "mother_maiden_name": "", "mother_last_name": "", "father_first_name": "", "father_last_name": "", "birth_hospital": "Richmond Memorial", "searching_for": "Child"}}, {"model": "sherlock.about", "pk": 17, "fields": {"user": 17, "biography": "", "birthdate": "1993-03-21", "city_of_birth": "Albany", "state_of_birth": "New York (NY)", "country_of_birth": "", "sex_at_birth": "Male", "eye_color": "Hazel", "mother_first_name": "", "mother_maiden_name": "", "mother_last_name": "", "father_first_name": "", "father_last_name": "", "birth_hospital": "St. John Hospital", "searching_for": "Parent"}}, {"model": "sherlock.about", "pk": 18, "fields": {"user": 18, "biography": "", "birthdate": "1979-04-04", "city_of_birth": "Phoenix", "state_of_birth": "Arizona (AZ)", "country_of_birth": "", "sex_at_birth": "Male", "eye_color": "Gray", "mother_first_name": "", "mother_maiden_name": "", "mother_last_name": "", "father_first_name": "", "father_last_name": "", "birth_hospital": "Johns Hopkins Hospital", "searching_for": "Child"}}, {"model": "sherlock.about", "pk": 19, "fields": {"user": 19, "biography": "", "birthdate": "1995-12-27", "city_of_birth": "Lansing", "state_of_birth": "Michigan (MI)", "country_of_birth": "", "sex_at_birth": "Female", "eye_color": "Black", "mother_first_name": "", "mother_maiden_name": "", "mother_last_name": "", "father_first_name": "", "father_last_name": "", "birth_hospital": "St. Saint Hospital", "searching_for": "Uncle"}}, {"model": "sherlock.about", "pk": 20, "fields": {"user": 20, "biography": "", "birthdate": "1988-06-25", "city_of_birth": "Seattle", "state_of_birth": "Washington (WA)", "country_of_birth": "", "sex_at_birth": "Male", "eye_color": "Green", "mother_first_name": "", "mother_maiden_name": "", "mother_last_name": "", "father_first_name": "", "father_last_name": "", "birth_hospital": "Sacred Heart Hospital", "searching_for": "Parent"}}, {"model": "sherlock.about", "pk": 21, "fields": {"user": 21, "biography": "", "birthdate": "1983-09-16", "city_of_birth": "Austin", "state_of_birth": "Texas (TX)", "country_of_birth": "", "sex_at_birth": "Female", "eye_color": "Black", "mother_first_name": "", "mother_maiden_name": "", "mother_last_name": "", "father_first_name": "", "father_last_name": "", "birth_hospital": "General Hospital", "searching_for": "Parent"}}]